openimis_be_payment-1.10.0.dist-info/licenses/LICENSE.md
payment/__init__.py
payment/admin.py
payment/apps.py
payment/gql_mutations.py
payment/gql_queries.py
payment/models.py
payment/schema.py
payment/services.py
payment/signals.py
payment/test_helpers.py
payment/urls.py
payment/views.py
payment/migrations/0001_initial.py
payment/migrations/0002_incorrect_name.py
payment/migrations/0003_auto_20220401_1149.py
payment/migrations/0004_update_django_scheme_with_missing_fields.py
payment/migrations/0005_set_managed_to_true.py
payment/migrations/0006_missing_fields_OP-1560.py
payment/migrations/0008_payment_serial_fix.py
payment/migrations/0009_alter_paymentdetail_insurance_number.py
payment/migrations/__init__.py
payment/tests/__init__.py
payment/tests/tests_gql.py
payment/tests/tests_service.py
openimis_be_payment-1.10.0.dist-info/METADATA
openimis_be_payment-1.10.0.dist-info/WHEEL
openimis_be_payment-1.10.0.dist-info/top_level.txt
openimis_be_payment-1.10.0.dist-info/RECORD
